CHANGES.rst
CONTRIBUTORS.rst
LICENSE.txt
MANIFEST.in
README.rst
setup.py
docs/Makefile
docs/__init__.py
docs/conf.py
docs/index.rst
docs/requirements.txt
docs/api/isbn_validator.rst
src/isbn_validator/__init__.py
src/isbn_validator/isbn_validator.py
src/isbn_validator.egg-info/PKG-INFO
src/isbn_validator.egg-info/SOURCES.txt
src/isbn_validator.egg-info/dependency_links.txt
src/isbn_validator.egg-info/not-zip-safe
src/isbn_validator.egg-info/requires.txt
src/isbn_validator.egg-info/top_level.txt