Metadata-Version: 1.1
Name: isbn-validator
Version: 1.0.0
Summary: ISBN validation module. MIT license.
Home-page: https://github.com/edeposit/isbn_validator
Author: Edeposit team
Author-email: edeposit@email.cz
License: MIT
Platform: UNKNOWN
Classifier: Programming Language :: Python :: 2.7
Classifier: License :: OSI Approved :: MIT License
Classifier: Topic :: Software Development :: Libraries :: Python Modules
